anirtic_calculator/__init__.py
anirtic_calculator/calculator.py
anirtic_calculator-0.0.4.dist-info/LICENSE
anirtic_calculator-0.0.4.dist-info/METADATA
anirtic_calculator-0.0.4.dist-info/WHEEL
anirtic_calculator-0.0.4.dist-info/top_level.txt
anirtic_calculator-0.0.4.dist-info/RECORD
