Metadata-Version: 2.1
Name: anirtic-calculator
Version: 0.0.4
Summary: Basic operations calculator
Home-page: https://github.com/anirtic/anirtic_calculator
Author: Matas Dziugas
Author-email: matasdziugas@gmail.com
Classifier: Programming Language :: Python :: 3
Classifier: License :: OSI Approved :: MIT License
Classifier: Operating System :: OS Independent
Requires-Python: >=3.7
License-File: LICENSE
